{
    "wallpaper": "/home/juan/Pictures/Wallpapers/panther4k2.jpg",
    "alpha": "100",
    "special": {
        "background": "#030303",
        "foreground": "#d6d5da",
        "cursor": "#d6d5da"
    },
    "colors": {
        "color0": "#030303",
        "color1": "#62676D",
        "color2": "#828279",
        "color3": "#706088",
        "color4": "#B032C9",
        "color5": "#79878D",
        "color6": "#9AA2A4",
        "color7": "#d6d5da",
        "color8": "#959598",
        "color9": "#62676D",
        "color10": "#828279",
        "color11": "#706088",
        "color12": "#B032C9",
        "color13": "#79878D",
        "color14": "#9AA2A4",
        "color15": "#d6d5da"
    }
}