{
    "wallpaper": "/home/juan/Pictures/Wallpapers/smoke4k.jpg",
    "alpha": "100",
    "special": {
        "background": "#030404",
        "foreground": "#99c3d2",
        "cursor": "#99c3d2"
    },
    "colors": {
        "color0": "#030404",
        "color1": "#8F417C",
        "color2": "#7C3E81",
        "color3": "#1A6C8C",
        "color4": "#616893",
        "color5": "#BB4C9F",
        "color6": "#1295AC",
        "color7": "#99c3d2",
        "color8": "#6b8893",
        "color9": "#8F417C",
        "color10": "#7C3E81",
        "color11": "#1A6C8C",
        "color12": "#616893",
        "color13": "#BB4C9F",
        "color14": "#1295AC",
        "color15": "#99c3d2"
    }
}